alchemy_graph/__init__.py
alchemy_graph/__version__.py
alchemy_graph/main.py
alchemy_graph/types.py
alchemy_graph/utils.py
alchemy_graph-0.1.3.dist-info/LICENSE
alchemy_graph-0.1.3.dist-info/METADATA
alchemy_graph-0.1.3.dist-info/WHEEL
alchemy_graph-0.1.3.dist-info/RECORD
