Metadata-Version: 2.1
Name: alchemy-graph
Version: 0.1.3
Summary: 
Home-page: https://github.com/kieled/alchemy_graph
Keywords: strawberry-graphql,sqlalchemy-mapper,sqlalchemy,strawberry,mapper,dict
Author: Kiel Ed
Author-email: kieledssh@gmail.com
Requires-Python: >=3.10,<4.0
Classifier: Intended Audience :: Developers
Classifier: License :: OSI Approved :: Apache Software License
Classifier: Programming Language :: Python
Classifier: Programming Language :: Python :: 3
Classifier: Programming Language :: Python :: 3.10
Classifier: Programming Language :: Python :: 3.11
Classifier: Programming Language :: Python :: Implementation :: PyPy
Classifier: Topic :: Software Development :: Libraries :: Python Modules
Requires-Dist: sqlalchemy (>=2,<3)
Requires-Dist: strawberry-graphql (>=0,<1)
Project-URL: Repository, https://github.com/kieled/alchemy_graph
